interpret_extension/__init__.py
interpret_extension/_version.py
interpret_extension/develop.py
interpret_extension/api/__init__.py
interpret_extension/api/base.py
interpret_extension/api/templates.py
interpret_extension/blackbox/__init__.py
interpret_extension/blackbox/_lime.py
interpret_extension/blackbox/_partialdependence.py
interpret_extension/blackbox/_permutationimportance.py
interpret_extension/blackbox/_sensitivity.py
interpret_extension/blackbox/_shap.py
interpret_extension/data/__init__.py
interpret_extension/data/_response.py
interpret_extension/ext/__init__.py
interpret_extension/ext/examples.py
interpret_extension/ext/extension.py
interpret_extension/ext/extension_utils.py
interpret_extension/ext/blackbox/__init__.py
interpret_extension/ext/data/__init__.py
interpret_extension/ext/glassbox/__init__.py
interpret_extension/ext/greybox/__init__.py
interpret_extension/ext/perf/__init__.py
interpret_extension/ext/provider/__init__.py
interpret_extension/glassbox/__init__.py
interpret_extension/glassbox/_aplr.py
interpret_extension/glassbox/_decisiontree.py
interpret_extension/glassbox/_linear.py
interpret_extension/glassbox/_lineardiscriminantanalysis.py
interpret_extension/glassbox/_naivebayes.py
interpret_extension/glassbox/_skoperules.py
interpret_extension/glassbox/_tan.py
interpret_extension/glassbox/_ebm/__init__.py
interpret_extension/glassbox/_ebm/_bin.py
interpret_extension/glassbox/_ebm/_boost.py
interpret_extension/glassbox/_ebm/_ebm.py
interpret_extension/glassbox/_ebm/_json.py
interpret_extension/glassbox/_ebm/_merge_ebms.py
interpret_extension/glassbox/_ebm/_multiclass.py
interpret_extension/glassbox/_ebm/_tensor.py
interpret_extension/glassbox/_ebm/_utils.py
interpret_extension/glassbox/_ebm/_research/__init__.py
interpret_extension/glassbox/_ebm/_research/_group_importance.py
interpret_extension/glassbox/_nam/__init__.py
interpret_extension/glassbox/_nam/data/__init__.py
interpret_extension/glassbox/_nam/data/data.py
interpret_extension-0.1.6.dist-info/METADATA
interpret_extension-0.1.6.dist-info/WHEEL
interpret_extension-0.1.6.dist-info/top_level.txt
interpret_extension-0.1.6.dist-info/RECORD
